weatherApp/__init__.py
weatherApp/weather.py
malekhoufel_weather_app-0.4.0.dist-info/METADATA
malekhoufel_weather_app-0.4.0.dist-info/WHEEL
malekhoufel_weather_app-0.4.0.dist-info/top_level.txt
malekhoufel_weather_app-0.4.0.dist-info/RECORD
