Metadata-Version: 2.1
Name: malekhoufel-weather-app
Version: 0.4.0
Summary: application météo
Home-page: https://github.com/malekhoufel/weatherApp.git
Author: Malek
Author-email: abdelmalek.houfel@sinay.fr
License: UNKNOWN
Platform: UNKNOWN
Classifier: Programming Language :: Python :: 3
Classifier: License :: OSI Approved :: MIT License
Classifier: Operating System :: OS Independent
Requires-Python: >=3.6
Requires-Dist: requests
